fakenode/__init__.py
fakenode/fakeshell.py
fakenode/server.py
fakenode-0.4.0.dist-info/METADATA
fakenode-0.4.0.dist-info/WHEEL
fakenode-0.4.0.dist-info/entry_points.txt
fakenode-0.4.0.dist-info/top_level.txt
fakenode-0.4.0.dist-info/RECORD
