Metadata-Version: 2.4
Name: fakenode
Version: 0.4.0
Summary: A simulated Autonomi node for testing node management software
Author-email: Troy Johnson <troy@weave.sh>
License: MIT
Project-URL: Homepage, https://github.com/ambled/fakenode
Project-URL: Issues, https://github.com/ambled/fakenode/issues
Classifier: Development Status :: 3 - Alpha
Classifier: Intended Audience :: Developers
Classifier: Programming Language :: Python :: 3
Classifier: Programming Language :: Python :: 3.9
Classifier: Programming Language :: Python :: 3.10
Classifier: Programming Language :: Python :: 3.11
Classifier: Programming Language :: Python :: 3.12
Classifier: Programming Language :: Python :: 3.13
Classifier: Programming Language :: Python :: 3.14
Requires-Python: >=3.9
Requires-Dist: flask>=3.0.0
